django_jwt_allauth-1.2.3.dist-info/licenses/AUTHORS
django_jwt_allauth-1.2.3.dist-info/licenses/LICENSE
jwt_allauth/__init__.py
jwt_allauth/adapter.py
jwt_allauth/app_settings.py
jwt_allauth/apps.py
jwt_allauth/constants.py
jwt_allauth/exceptions.py
jwt_allauth/models.py
jwt_allauth/permissions.py
jwt_allauth/roles.py
jwt_allauth/test.py
jwt_allauth/urls.py
jwt_allauth/utils.py
jwt_allauth/bin/__init__.py
jwt_allauth/bin/jwt_allauth.py
jwt_allauth/locale/cs/LC_MESSAGES/django.po
jwt_allauth/locale/de/LC_MESSAGES/django.po
jwt_allauth/locale/es/LC_MESSAGES/django.po
jwt_allauth/locale/fr/LC_MESSAGES/django.po
jwt_allauth/locale/ko/LC_MESSAGES/django.po
jwt_allauth/locale/pl/LC_MESSAGES/django.po
jwt_allauth/locale/pt_BR/LC_MESSAGES/django.po
jwt_allauth/locale/ru/LC_MESSAGES/django.po
jwt_allauth/locale/tr/LC_MESSAGES/django.po
jwt_allauth/locale/zh_Hans/LC_MESSAGES/django.po
jwt_allauth/locale/zh_Hant/LC_MESSAGES/django.po
jwt_allauth/login/__init__.py
jwt_allauth/login/serializers.py
jwt_allauth/login/views.py
jwt_allauth/logout/__init__.py
jwt_allauth/logout/serializers.py
jwt_allauth/logout/views.py
jwt_allauth/mfa/__init__.py
jwt_allauth/mfa/adapter.py
jwt_allauth/mfa/permissions.py
jwt_allauth/mfa/serializers.py
jwt_allauth/mfa/storage.py
jwt_allauth/mfa/urls.py
jwt_allauth/mfa/views.py
jwt_allauth/password_change/__init__.py
jwt_allauth/password_change/serializers.py
jwt_allauth/password_change/views.py
jwt_allauth/password_reset/__init__.py
jwt_allauth/password_reset/models.py
jwt_allauth/password_reset/permissions.py
jwt_allauth/password_reset/serializers.py
jwt_allauth/password_reset/views.py
jwt_allauth/registration/__init__.py
jwt_allauth/registration/app_settings.py
jwt_allauth/registration/serializers.py
jwt_allauth/registration/urls.py
jwt_allauth/registration/views.py
jwt_allauth/registration/email_verification/__init__.py
jwt_allauth/registration/email_verification/serializers.py
jwt_allauth/registration/email_verification/views.py
jwt_allauth/templates/email/verified.html
jwt_allauth/templates/email/admin_invite/email_message.html
django_jwt_allauth-1.2.3.dist-info/METADATA
django_jwt_allauth-1.2.3.dist-info/WHEEL
django_jwt_allauth-1.2.3.dist-info/entry_points.txt
django_jwt_allauth-1.2.3.dist-info/top_level.txt
django_jwt_allauth-1.2.3.dist-info/RECORD
