Metadata-Version: 2.4
Name: django-jwt-allauth
Version: 1.2.3
Summary: Powerful JWT-allauth authentication for Django REST Framework that keeps the device session alive by renewing and whitelisting the refresh token.
Author-email: Fernando Castellanos <fcastellanos.dev@gmail.com>
Project-URL: Homepage, https://github.com/castellanos-dev/jwt-allauth
Project-URL: Repository, https://github.com/castellanos-dev/jwt-allauth
Project-URL: Documentation, https://jwt-allauth.readthedocs.io/
Keywords: django,rest,auth,registration,rest-framework,django-registration,api,allauth,jwt,whitelist
Classifier: Framework :: Django
Classifier: Intended Audience :: Developers
Classifier: Intended Audience :: System Administrators
Classifier: Operating System :: OS Independent
Classifier: Topic :: Software Development
Classifier: Programming Language :: Python :: 3
Classifier: Programming Language :: Python :: 3.10
Classifier: Programming Language :: Python :: 3.11
Classifier: Programming Language :: Python :: 3.12
Requires-Python: >=3.10
License-File: LICENSE
License-File: AUTHORS
Requires-Dist: Django<6.0,>=4.2
Requires-Dist: djangorestframework<4.0,>=3.15
Requires-Dist: six<2.0,>=1.9
Requires-Dist: django-allauth<66.0,>=65.5
Requires-Dist: djangorestframework-simplejwt<6.0,>=5.3.1
Requires-Dist: django-user-agents<1.0,>=0.4
Provides-Extra: mfa
Requires-Dist: django-allauth[mfa]<66.0,>=65.5; extra == "mfa"
Requires-Dist: fido2<2.0.0; extra == "mfa"
Provides-Extra: test
Requires-Dist: responses>=0.5.0; extra == "test"
Dynamic: license-file
